brixy/__init__.py
brixy/logging.py
brixy-0.2.1.dist-info/LICENSE
brixy-0.2.1.dist-info/METADATA
brixy-0.2.1.dist-info/WHEEL
brixy-0.2.1.dist-info/top_level.txt
brixy-0.2.1.dist-info/RECORD
