Metadata-Version: 2.1
Name: brixy
Version: 0.2.1
Summary: Helpers for developing solution on Databricks and PySpark
Author-email: Dennis Egert <degertsa@yahoo.com>
Maintainer-email: Dennis Egert <degertsa@yahoo.com>
License: MIT license
Project-URL: bugs, https://github.com/egde/brixy/issues
Project-URL: changelog, https://github.com/egde/brixy/releases
Project-URL: homepage, https://github.com/egde/brixy
License-File: LICENSE
Provides-Extra: dev
Requires-Dist: coverage; extra == "dev"
Requires-Dist: mypy; extra == "dev"
Requires-Dist: pytest; extra == "dev"
Requires-Dist: ruff; extra == "dev"
